concierge/__init__.py
concierge/telemetry.py
concierge/adapters/__init__.py
concierge/adapters/base.py
concierge/adapters/fastmcp_adapter.py
concierge/adapters/raw_server_adapter.py
concierge/backends/__init__.py
concierge/backends/base_provider.py
concierge/backends/search_backend.py
concierge/backends/vanilla_backend.py
concierge/core/__init__.py
concierge/core/widget.py
concierge/templates/chatgpt/README.md
concierge/templates/chatgpt/main.py
concierge/templates/chatgpt/requirements.txt
concierge/templates/chatgpt/assets/package.json
concierge/templates/chatgpt/assets/entrypoints/pizzaz-albums.html
concierge/templates/chatgpt/assets/entrypoints/pizzaz-carousel.html
concierge/templates/chatgpt/assets/entrypoints/pizzaz-list.html
concierge/templates/chatgpt/assets/entrypoints/pizzaz-shop.html
concierge/templates/chatgpt/assets/entrypoints/pizzaz.html
concierge/templates/chatgpt/assets/src/pizzaz/markers.json
concierge/templates/chatgpt/assets/src/pizzaz-albums/albums.json
concierge_cli/__init__.py
concierge_sdk-0.3.3.dist-info/licenses/LICENSE
concierge_sdk-0.3.3.dist-info/METADATA
concierge_sdk-0.3.3.dist-info/WHEEL
concierge_sdk-0.3.3.dist-info/entry_points.txt
concierge_sdk-0.3.3.dist-info/top_level.txt
concierge_sdk-0.3.3.dist-info/RECORD
