Metadata-Version: 2.4
Name: concierge-sdk
Version: 0.3.3
Summary: Deploy production grade MCP apps in seconds
Requires-Python: >=3.9
License-File: LICENSE
Requires-Dist: mcp>=1.0.0
Requires-Dist: httpx>=0.25.0
Provides-Extra: all
Requires-Dist: sentence-transformers>=2.0.0; extra == "all"
Requires-Dist: numpy>=1.24.0; extra == "all"
Dynamic: license-file
